[
    {
        "author": "Pete Hunt",
        "text": "This is one bad-ass comment"
    },
    {
        "author": "Jordan Walke",
        "text": "This is *another* awesome comment"
    },
    {
        "author": "Todd Rundgren",
        "text": "Throw Money!"
    },
    {
        "author": "Ron Swanson",
        "text": "You would be stunning as a brunette"
    },
    {
        "author": "Macho Man",
        "text": "Oh yeeah"
    },
    {
        "author": "Jack Burton",
        "text": "I just want my truck back"
    },
    {
        "author": "Wha",
        "text": "zup"
    }
]